nonebot_plugin_multi_chatgpt/__init__.py
nonebot_plugin_multi_chatgpt/config.py
nonebot_plugin_multi_chatgpt/img_switcher.py
nonebot_plugin_multi_chatgpt/path.py
nonebot_plugin_multi_chatgpt/utils.py
nonebot_plugin_multi_chatgpt-3.0.0.dist-info/WHEEL
nonebot_plugin_multi_chatgpt-3.0.0.dist-info/METADATA
nonebot_plugin_multi_chatgpt-3.0.0.dist-info/RECORD
