Metadata-Version: 2.1
Name: nonebot-plugin-multi-chatgpt
Version: 3.0.0
Summary: 
Author: chrisyy
Author-email: 1017975501@qq.com
Requires-Python: >=3.8,<4.0
Classifier: Programming Language :: Python :: 3
Classifier: Programming Language :: Python :: 3.8
Classifier: Programming Language :: Python :: 3.9
Classifier: Programming Language :: Python :: 3.10
Classifier: Programming Language :: Python :: 3.11
Requires-Dist: nonebot-adapter-onebot (>=2.1.5,<3.0.0)
Requires-Dist: nonebot-plugin-apscheduler (>=0.2.0,<0.3.0)
Requires-Dist: nonebot-plugin-htmlrender (>=0.2.0.1,<0.3.0.0)
Requires-Dist: nonebot2 (>=2.0.0rc2,<3.0.0)
Requires-Dist: pyyaml (>=5.4.1,<6.0.0)
Requires-Dist: revchatgpt (==0.0.43)
